Compiled from "ForeachPrinciple.java"
public class com.pattern.tutor.deepinjvm.principle.ForeachPrinciple {
  public com.pattern.tutor.deepinjvm.principle.ForeachPrinciple();
    Code:
       0: aload_0
       1: invokespecial #1                  // Method java/lang/Object."<init>":()V
       4: return

  public static void main(java.lang.String[]);
    Code:
       0: new           #2                  // class com/pattern/tutor/deepinjvm/principle/ForeachPrinciple$1
       3: dup
       4: invokespecial #3                  // Method com/pattern/tutor/deepinjvm/principle/ForeachPrinciple$1."<init>":()V
       7: astore_1
       8: aload_1
       9: invokeinterface #4,  1            // InterfaceMethod java/util/List.iterator:()Ljava/util/Iterator;
      14: astore_2
      15: aload_2
      16: invokeinterface #5,  1            // InterfaceMethod java/util/Iterator.hasNext:()Z
      21: ifeq          54
      24: aload_2
      25: invokeinterface #6,  1            // InterfaceMethod java/util/Iterator.next:()Ljava/lang/Object;
      30: checkcast     #7                  // class java/lang/String
      33: astore_3
      34: ldc           #8                  // String history
      36: aload_3
      37: invokevirtual #9                  // Method java/lang/String.equals:(Ljava/lang/Object;)Z
      40: ifeq          51
      43: aload_1
      44: aload_3
      45: invokeinterface #10,  2           // InterfaceMethod java/util/List.remove:(Ljava/lang/Object;)Z
      50: pop
      51: goto          15
      54: getstatic     #11                 // Field java/lang/System.out:Ljava/io/PrintStream;
      57: aload_1
      58: invokevirtual #12                 // Method java/io/PrintStream.println:(Ljava/lang/Object;)V
      61: return
}
