Compiled from "ScaryExpressionExample.java"
public class com.jangz.syntax.scary.ScaryExpressionExample {
  public com.jangz.syntax.scary.ScaryExpressionExample();
    Code:
       0: aload_0
       1: invokespecial #1                  // Method java/lang/Object."<init>":()V
       4: return

  public static void main(java.lang.String[]);
    Code:
       0: iconst_1
       1: istore_1
       2: iload_1
       3: iinc          1, 1
       6: istore_1
       7: iconst_1
       8: istore_2
       9: iinc          2, 1
      12: iload_2
      13: istore_2
      14: return
}
